README.md
setup.py
pysiren/__init__.py
pysiren/error.py
pysiren/renderer.py
pysiren.egg-info/PKG-INFO
pysiren.egg-info/SOURCES.txt
pysiren.egg-info/dependency_links.txt
pysiren.egg-info/requires.txt
pysiren.egg-info/top_level.txt
pysiren/entities/__init__.py
pysiren/entities/action.py
pysiren/entities/entity.py
pysiren/entities/field.py
pysiren/entities/field_type.py
pysiren/entities/field_value_object.py
pysiren/entities/link.py
pysiren/entities/media_type.py
pysiren/entities/method.py
pysiren/entities/rel.py
pysiren/helpers/__init__.py
pysiren/helpers/pagination.py
test/test_pagination.py
test/test_performance.py
test/test_renderer.py
test/test_siren.py