Metadata-Version: 1.1
Name: pysiren
Version: 0.3.5
Summary: Utility for generating Siren Hypermedia compliant payloads.
Home-page: https://github.com/mdziemianko/pysiren
Author: Michal Dziemianko
Author-email: michal.dziemianko@gmail.com
License: UNKNOWN
Keywords: REST HATEOAS Hypermedia RESTful SIREN HAL API JSONAPI web framework
Platform: UNKNOWN
Classifier: Development Status :: 3 - Alpha
Classifier: License :: OSI Approved :: Mozilla Public License 2.0 (MPL 2.0)
Classifier: Programming Language :: Python
Classifier: Programming Language :: Python :: 3
Classifier: Programming Language :: Python :: 3.4
Classifier: Programming Language :: Python :: 3.5
Classifier: Programming Language :: Python :: 3.6
Classifier: Programming Language :: Python :: Implementation :: PyPy
Classifier: Topic :: Software Development :: Libraries :: Python Modules
